{"dialogues":{"aa":{"_pathTillHere":["START"],"_allText":["Hey, i'm a first dialogue, can u believe it?","Yeah, that's super cool. I am a second dialogue :)"],"_options":["Option 1","Option 2"],"_typeSpeed":0.02,"_textColor":"ffffff","_imageConfig":{"island_healthy":true}},"bb":{"_pathTillHere":["aa1"],"_allText":["DDDD 1 LOL ","D2 dialogue 2","Dialogue 3 lol hahaha"],"_options":["Option 11","Option 22","Option 33","Option 44"],"_typeSpeed":0.02,"_textColor":"ff2929","_imageConfig":{"island_healthy":false,"island_destroyed":true}},"cc":{"_pathTillHere":["bb1","bb3"],"_allText":["another option of text"],"_options":["Option 11","Option 22"],"_typeSpeed":0.02,"_textColor":"ffffff","_imageConfig":{}},"dd":{"_pathTillHere":["bb2","bb4"],"_allText":["again, different one","this one has two texts lol"],"_options":["Option 1","Option 2","Option 3","Option 4"],"_typeSpeed":0.02,"_textColor":"ffffff","_imageConfig":{"img1":true,"img2":true}}},"allImages":[{"_imageName":"island_healthy","_xPos":0.0,"_yPos":0.0,"_layer":0},{"_imageName":"island_destroyed","_xPos":0.0,"_yPos":0.0,"_layer":0},{"_imageName":"img1","_xPos":500.0,"_yPos":200.0,"_layer":1},{"_imageName":"img2","_xPos":-300.0,"_yPos":100.0,"_layer":2}]}